ipfs_model_manager/__init__.py
ipfs_model_manager/ipfs_model_manager.py
ipfs_model_manager/test_fio.py
ipfs_model_manager/aria2/aria2.py
ipfs_model_manager/aria2/aria2c
ipfs_model_manager/config/__init__.py
ipfs_model_manager/config/config.py
ipfs_model_manager/config/config.toml
ipfs_model_manager/config/config_template.toml
ipfs_model_manager/s3_kit/s3_kit.py
ipfs_model_manager/test/test_fio.py
ipfs_model_manager/test/test_hf_ipfs.py
ipfs_model_manager-0.0.1.dist-info/LICENSE
ipfs_model_manager-0.0.1.dist-info/METADATA
ipfs_model_manager-0.0.1.dist-info/WHEEL
ipfs_model_manager-0.0.1.dist-info/top_level.txt
ipfs_model_manager-0.0.1.dist-info/RECORD
